sociallinks/__init__.py
sociallinks/basic.py
sociallinks/constants.py
sociallinks/core.py
sociallinks/exceptions.py
sociallinks/platforms.py
sociallinks/py.typed
social_links-1.3.0.dist-info/METADATA
social_links-1.3.0.dist-info/WHEEL
social_links-1.3.0.dist-info/licenses/LICENSE
social_links-1.3.0.dist-info/RECORD
