Metadata-Version: 2.4
Name: social-links
Version: 1.3.0
Summary: Python library to validate, sanitize, and detect social media URLs. Support for LinkedIn, Instagram, TikTok, X/Twitter, GitHub, Facebook, YouTube, and 50+ platforms. Features automatic URL normalization and zero dependencies. Easy to use, regex-powered, and customizable.
Project-URL: Homepage, https://github.com/ysskrishna/social-links
Project-URL: Documentation, https://ysskrishna.github.io/social-links/
Project-URL: Repository, https://github.com/ysskrishna/social-links.git
Project-URL: Issues, https://github.com/ysskrishna/social-links/issues
Project-URL: Changelog, https://github.com/ysskrishna/social-links/blob/main/CHANGELOG.md
Project-URL: Discussions, https://github.com/ysskrishna/social-links/discussions
Author-email: ysskrishna <sivasaikrishnassk@gmail.com>
License: MIT
License-File: LICENSE
Keywords: api reference,behance,bluesky,changelog,contribution guide,detect,discord,dribbble,facebook,github,instagram,linkedin,mastodon,medium,mit license,normalize,open source,pinterest,python library,quora,reddit,regex,regular expression,sanitize,social media links,social-links,tiktok,twitter,url parser,url validation,validate,version history,x,youtube,ysskrishna
Classifier: Development Status :: 5 - Production/Stable
Classifier: Intended Audience :: Developers
Classifier: License :: OSI Approved :: MIT License
Classifier: Operating System :: OS Independent
Classifier: Programming Language :: Python :: 3
Classifier: Programming Language :: Python :: 3.8
Classifier: Programming Language :: Python :: 3.9
Classifier: Programming Language :: Python :: 3.10
Classifier: Programming Language :: Python :: 3.11
Classifier: Programming Language :: Python :: 3.12
Classifier: Topic :: Internet :: WWW/HTTP :: Dynamic Content
Classifier: Topic :: Software Development :: Libraries :: Python Modules
Classifier: Topic :: Text Processing :: Markup
Classifier: Topic :: Utilities
Requires-Python: >=3.8
